penelopedefillama/__init__.py
penelopedefillama/schemas.py
penelopedefillama/service.py
penelopedefillama-0.1.1.dist-info/METADATA
penelopedefillama-0.1.1.dist-info/WHEEL
penelopedefillama-0.1.1.dist-info/entry_points.txt
penelopedefillama-0.1.1.dist-info/RECORD
