Metadata-Version: 2.4
Name: penelopedefillama
Version: 0.1.1
Summary: Package to use Defillama API
Requires-Python: >=3.12
Requires-Dist: pydantic>=2.11.7
Requires-Dist: requests>=2.32.5
